gunaltest/__init__.py
gunaltest/app.py
testgunal123-0.0.2.dist-info/LICENSE
testgunal123-0.0.2.dist-info/METADATA
testgunal123-0.0.2.dist-info/WHEEL
testgunal123-0.0.2.dist-info/top_level.txt
testgunal123-0.0.2.dist-info/RECORD
