Metadata-Version: 2.1
Name: testgunal123
Version: 0.0.2
Summary: gunal-testing
Home-page: UNKNOWN
Author: Gunal
Author-email: gunalr00@gmail.com
License: UNKNOWN
Platform: UNKNOWN
Classifier: Development Status :: 1 - Planning
Classifier: Intended Audience :: Developers
Classifier: Programming Language :: Python :: 3
Classifier: Operating System :: Unix
Classifier: Operating System :: MacOS :: MacOS X
Classifier: Operating System :: Microsoft :: Windows
License-File: LICENSE
